dump2json.py
setup.cfg
setup.py
pytest_dump2json.egg-info/PKG-INFO
pytest_dump2json.egg-info/SOURCES.txt
pytest_dump2json.egg-info/dependency_links.txt
pytest_dump2json.egg-info/entry_points.txt
pytest_dump2json.egg-info/pbr.json
pytest_dump2json.egg-info/requires.txt
pytest_dump2json.egg-info/top_level.txt
test/test_me.py