Metadata-Version: 1.1
Name: pytest-dump2json
Version: 0.1.0
Summary: A pytest plugin for dumping test results to json.
Home-page: https://github.com/d6e/pytest-dump2json
Author: Danielle Jenkins
Author-email: jenkinda@uw.edu
License: UNKNOWN
Download-URL: https://github.com/d6e/pytest-dump2json/archive/0.1.0.zip
Keywords: testing,pytest,json
Platform: UNKNOWN
